prgconfig.py
prgconfig-1.0.0.dist-info/LICENSE
prgconfig-1.0.0.dist-info/WHEEL
prgconfig-1.0.0.dist-info/METADATA
prgconfig-1.0.0.dist-info/RECORD
