Metadata-Version: 2.1
Name: prgconfig
Version: 1.0.0
Summary: Configuration manager using toml language.
Home-page: https://gitlab.com/remytms/prgconfig
License: GPL-3.0-or-later
Keywords: config,toml,unix
Author: Rémy Taymans
Author-email: remytms@tsmail.eu
Requires-Python: >=3.5,<4.0
Classifier: Development Status :: 4 - Beta
Classifier: Intended Audience :: Developers
Classifier: License :: OSI Approved :: GNU General Public License v3 or later (GPLv3+)
Classifier: Operating System :: POSIX
Classifier: Operating System :: Unix
Classifier: Programming Language :: Python :: 3
Classifier: Programming Language :: Python :: 3.5
Classifier: Programming Language :: Python :: 3.6
Classifier: Programming Language :: Python :: 3.7
Classifier: Programming Language :: Python :: 3.8
Classifier: Programming Language :: Python :: 3.9
Classifier: Programming Language :: Python :: Implementation :: CPython
Classifier: Topic :: Software Development :: Libraries
Requires-Dist: toml (>=0.10.2,<0.11.0)
Project-URL: Bug Tracker, https://gitlab.com/remytms/prgconfig/-/issues
Project-URL: Repository, https://gitlab.com/remytms/prgconfig
